{
  "compile": {
    "status": "pass",
    "output": {
      "stdout": "",
      "stderr": ""
    }
  },
  "run": {
    "status": "pass",
    "output": "[TIMING] mmap_columns: 0.07 ms\n[TIMING] scan_filter_aggregate: 23.61 ms\n[TIMING] output: 0.24 ms\n[TIMING] total: 23.97 ms\n",
    "stderr": "",
    "duration_ms": 50
  },
  "validation": {
    "status": "pass",
    "output": "{\n  \"match\": true,\n  \"queries\": {\n    \"Q6\": {\n      \"rows_expected\": 1,\n      \"rows_actual\": 1,\n      \"match\": true\n    }\n  }\n}\n"
  },
  "operation_timings": {
    "mmap_columns": 0.07,
    "scan_filter_aggregate": 23.61,
    "output": 0.24,
    "total": 23.97
  },
  "timing_ms": 23.73
}