{
  "compile": {
    "status": "pass",
    "output": {
      "stdout": "",
      "stderr": ""
    }
  },
  "run": {
    "status": "pass",
    "output": "[Q17] Starting execution...\n[Q17] brand_code=13 container_code=38\n[TIMING] dict_load: 0.05 ms\n[Q17] lineitem rows: 59986052\n[Q17] subquery: 2000000 distinct partkeys\n[TIMING] subquery: 14503.89 ms\n[Q17] part rows: 2000000\n[Q17] qualifying parts: 2044\n[TIMING] part_filter: 5.78 ms\n[TIMING] join_filter_aggregate: 1945.47 ms\n[Q17] Result: 3295493.51\n[Q17] Output written to /home/jl4492/GenDB/output/tpc-h/2026-02-16T20-31-57/queries/Q17/iter_0/results/Q17.csv\n[TIMING] output: 0.22 ms\n[TIMING] total: 16455.48 ms\n",
    "stderr": "",
    "duration_ms": 16522
  },
  "validation": {
    "status": "pass",
    "output": "{\n  \"match\": true,\n  \"queries\": {\n    \"Q17\": {\n      \"rows_expected\": 1,\n      \"rows_actual\": 1,\n      \"match\": true\n    }\n  }\n}\n"
  },
  "operation_timings": {
    "dict_load": 0.05,
    "subquery": 14503.89,
    "part_filter": 5.78,
    "join_filter_aggregate": 1945.47,
    "output": 0.22,
    "total": 16455.48
  },
  "timing_ms": 16455.26
}