{
  "query_id": "Q14",
  "iterations": [
    {
      "iteration": 1,
      "improved": true,
      "categories": [
        "io_bound"
      ],
      "timing_ms": 139,
      "validation": "pass"
    },
    {
      "iteration": 2,
      "improved": true,
      "categories": [],
      "timing_ms": 95.82,
      "validation": "pass"
    },
    {
      "iteration": 3,
      "improved": true,
      "categories": [],
      "timing_ms": 88.97,
      "validation": "pass"
    },
    {
      "iteration": 4,
      "improved": true,
      "categories": [],
      "timing_ms": 59.46,
      "validation": "pass"
    },
    {
      "iteration": 5,
      "improved": true,
      "categories": [
        "io_bound"
      ],
      "timing_ms": 29.55,
      "validation": "pass"
    }
  ]
}