{
  "compile": {
    "status": "pass",
    "output": {
      "stdout": "",
      "stderr": ""
    }
  },
  "run": {
    "status": "pass",
    "output": "[TIMING] dim_filter: 0.77 ms\n[TIMING] dim_filter_part: 54.97 ms\n[TIMING] build_joins: 87.49 ms\n[TIMING] build_joins_orders: 35.87 ms\n[TIMING] main_scan: 72.42 ms\n[TIMING] output: 0.17 ms\n[TIMING] total: 263.40 ms\n",
    "stderr": "",
    "duration_ms": 271
  },
  "validation": {
    "status": "pass",
    "output": "{\n  \"match\": true,\n  \"queries\": {\n    \"Q9\": {\n      \"rows_expected\": 175,\n      \"rows_actual\": 175,\n      \"match\": true\n    }\n  }\n}\n"
  },
  "operation_timings": {
    "dim_filter": 0.77,
    "dim_filter_part": 54.97,
    "build_joins": 87.49,
    "build_joins_orders": 35.87,
    "main_scan": 72.42,
    "output": 0.17,
    "total": 263.4
  },
  "timing_ms": 263.22999999999996
}