{
  "compile": {
    "status": "pass",
    "output": {
      "stdout": "",
      "stderr": ""
    }
  },
  "run": {
    "status": "pass",
    "output": "[TIMING] dim_filter: 0.03 ms\n[TIMING] build_joins: 1.92 ms\n[TIMING] main_scan: 11.84 ms\n[TIMING] output: 0.08 ms\n[TIMING] total: 21.30 ms\n",
    "stderr": "",
    "duration_ms": 25
  },
  "validation": {
    "status": "pass",
    "output": "{\n  \"match\": true,\n  \"queries\": {\n    \"Q6\": {\n      \"rows_expected\": 1,\n      \"rows_actual\": 1,\n      \"match\": true\n    }\n  }\n}\n"
  },
  "operation_timings": {
    "dim_filter": 0.03,
    "build_joins": 1.92,
    "main_scan": 11.84,
    "output": 0.08,
    "total": 21.3
  },
  "timing_ms": 21.220000000000002
}