{
  "compile": {
    "status": "pass",
    "output": {
      "stdout": "",
      "stderr": ""
    }
  },
  "run": {
    "status": "pass",
    "output": "[TIMING] load_dictionaries: 0.11 ms\n[TIMING] load_columns: 0.14 ms\n[TIMING] filter_region: 0.01 ms\n[TIMING] build_nation_lookup: 0.01 ms\n[TIMING] filter_orders: 184.38 ms\n[TIMING] build_supplier_map: 2.42 ms\n[TIMING] build_customer_map: 33.93 ms\n[TIMING] join_and_aggregate: 65.24 ms\n[TIMING] output: 0.17 ms\n[TIMING] total: 336.02 ms\n",
    "stderr": "",
    "duration_ms": 344
  },
  "validation": {
    "status": "pass",
    "output": "{\n  \"match\": true,\n  \"queries\": {\n    \"Q5\": {\n      \"rows_expected\": 5,\n      \"rows_actual\": 5,\n      \"match\": true\n    }\n  }\n}\n"
  },
  "operation_timings": {
    "load_dictionaries": 0.11,
    "load_columns": 0.14,
    "filter_region": 0.01,
    "build_nation_lookup": 0.01,
    "filter_orders": 184.38,
    "build_supplier_map": 2.42,
    "build_customer_map": 33.93,
    "join_and_aggregate": 65.24,
    "output": 0.17,
    "total": 336.02
  },
  "timing_ms": 335.84999999999997
}