{
  "query_id": "Q11",
  "iterations": [
    {
      "iteration": 1,
      "improved": true,
      "categories": [],
      "timing_ms": 95.89,
      "validation": "pass"
    },
    {
      "iteration": 2,
      "improved": false,
      "categories": [],
      "timing_ms": null,
      "validation": "skipped"
    },
    {
      "iteration": 3,
      "improved": false,
      "categories": [],
      "timing_ms": 114.53,
      "validation": "pass"
    },
    {
      "iteration": 4,
      "improved": true,
      "categories": [],
      "timing_ms": 92.61,
      "validation": "pass"
    },
    {
      "iteration": 5,
      "improved": false,
      "categories": [],
      "timing_ms": 2283.67,
      "validation": "fail"
    },
    {
      "iteration": 6,
      "improved": true,
      "categories": [],
      "timing_ms": 78.30000000000001,
      "validation": "pass"
    },
    {
      "iteration": 7,
      "improved": false,
      "categories": [],
      "timing_ms": 177.76999999999998,
      "validation": "pass"
    },
    {
      "iteration": 8,
      "improved": false,
      "categories": [],
      "timing_ms": 91.92,
      "validation": "pass"
    },
    {
      "iteration": 9,
      "improved": true,
      "categories": [],
      "timing_ms": 69.13,
      "validation": "pass"
    },
    {
      "iteration": 10,
      "improved": false,
      "categories": [],
      "timing_ms": 99.91000000000001,
      "validation": "pass"
    }
  ]
}