{
  "compile": {
    "status": "pass"
  },
  "run": {
    "status": "pass",
    "duration_ms": 10743
  },
  "validation": {
    "status": "fail",
    "details": {
      "match": false,
      "queries": {
        "Q6": {
          "rows_expected": 200,
          "rows_actual": 200,
          "match": false,
          "error": "3 row(s) differ",
          "sample_mismatches": [
            {
              "row": 0,
              "expected": [
                "ABBOTT LABORATORIES",
                "IS",
                "RevenueFromContractWithCustomerExcludingAssessedTax",
                "Net sales",
                "1188018000000.00",
                "650.00"
              ],
              "actual": [
                "ABBOTT LABORATORIES",
                "IS",
                "RevenueFromContractWithCustomerExcludingAssessedTax",
                "Net Sales",
                "981929000000.00",
                "220.00"
              ],
              "cell_details": [
                {
                  "expected": "Net sales",
                  "actual": "Net Sales",
                  "pattern": "string_mismatch",
                  "col": 3
                },
                {
                  "expected": "1188018000000.00",
                  "actual": "981929000000.00",
                  "abs_diff": 206089000000,
                  "magnitude": 1188018000000,
                  "relative_diff": 0.17347296,
                  "pattern": "value_mismatch",
                  "col": 4
                },
                {
                  "expected": "650.00",
                  "actual": "220.00",
                  "abs_diff": 430,
                  "magnitude": 650,
                  "relative_diff": 0.66153846,
                  "pattern": "value_mismatch",
                  "col": 5
                }
              ]
            },
            {
              "row": 1,
              "expected": [
                "ACCENTURE PLC",
                "IS",
                "Revenues",
                "Revenues",
                "1831336582000.00",
                "151.00"
              ],
              "actual": [
                "ABBOTT LABORATORIES",
                "IS",
                "RevenueFromContractWithCustomerExcludingAssessedTax",
                "Net sales",
                "1188018000000.00",
                "650.00"
              ],
              "cell_details": [
                {
                  "expected": "ACCENTURE PLC",
                  "actual": "ABBOTT LABORATORIES",
                  "pattern": "string_mismatch",
                  "col": 0
                },
                {
                  "expected": "Revenues",
                  "actual": "RevenueFromContractWithCustomerExcludingAssessedTax",
                  "pattern": "string_mismatch",
                  "col": 2
                },
                {
                  "expected": "Revenues",
                  "actual": "Net sales",
                  "pattern": "string_mismatch",
                  "col": 3
                },
                {
                  "expected": "1831336582000.00",
                  "actual": "1188018000000.00",
                  "abs_diff": 643318582000,
                  "magnitude": 1831336582000,
                  "relative_diff": 0.35128364,
                  "pattern": "value_mismatch",
                  "col": 4
                },
                {
                  "expected": "151.00",
                  "actual": "650.00",
                  "abs_diff": 499,
                  "magnitude": 151,
                  "relative_diff": 3.30463576,
                  "pattern": "value_mismatch",
                  "col": 5
                }
              ]
            },
            {
              "row": 3,
              "expected": [
                "ALPHABET INC.",
                "IS",
                "CostsAndExpenses",
                "Total costs and expenses",
                "1434493000000.00",
                "13.00"
              ],
              "actual": [
                "AMAZON COM INC",
                "IS",
                "CostOfGoodsAndServicesSold",
                "Cost of sales",
                "1966755000000.00",
                "13.00"
              ],
              "cell_details": [
                {
                  "expected": "ALPHABET INC.",
                  "actual": "AMAZON COM INC",
                  "pattern": "string_mismatch",
                  "col": 0
                },
                {
                  "expected": "CostsAndExpenses",
                  "actual": "CostOfGoodsAndServicesSold",
                  "pattern": "string_mismatch",
                  "col": 2
                },
                {
                  "expected": "Total costs and expenses",
                  "actual": "Cost of sales",
                  "pattern": "string_mismatch",
                  "col": 3
                },
                {
                  "expected": "1434493000000.00",
                  "actual": "1966755000000.00",
                  "abs_diff": 532262000000,
                  "magnitude": 1434493000000,
                  "relative_diff": 0.37104538,
                  "pattern": "value_mismatch",
                  "col": 4
                }
              ]
            }
          ],
          "mismatch_patterns": {
            "string_mismatch": 521,
            "value_mismatch": 377,
            "scale_error": 1
          }
        }
      }
    }
  },
  "optimization_target": "hot",
  "timing_ms": 10810.54,
  "hot_timing_ms": 10810.54,
  "operation_timings": {
    "data_loading": 54.12,
    "dim_filter": 90.28,
    "build_joins": 76.83,
    "main_scan": 10087.51,
    "aggregation_merge": 69.43,
    "sort_topk": 0.44,
    "output": 0.56,
    "total": 10676.03
  }
}