{
  "runId": "2026-02-14T01-28-16",
  "workload": "tpc-h",
  "startedAt": "2026-02-14T01:28:16.841Z",
  "status": "running",
  "dataDir": "/home/jl4492/GenDB/benchmarks/tpc-h/data/sf10",
  "gendbDir": "/home/jl4492/GenDB/benchmarks/tpc-h/gendb/tpch_sf10.gendb",
  "scaleFactor": 10,
  "maxIterations": 3,
  "model": "sonnet",
  "optimizationTarget": "execution_time",
  "phase1": {
    "status": "completed",
    "steps": {
      "workload_analysis": {
        "status": "completed",
        "startedAt": "2026-02-14T01:28:17.380Z",
        "completedAt": "2026-02-14T01:29:26.875Z"
      },
      "storage_design": {
        "status": "completed",
        "startedAt": "2026-02-14T01:29:26.876Z",
        "completedAt": "2026-02-14T01:36:02.861Z"
      },
      "data_ingestion": {
        "status": "completed",
        "completedAt": "2026-02-14T01:36:02.861Z"
      },
      "index_building": {
        "status": "completed",
        "completedAt": "2026-02-14T01:36:02.861Z"
      }
    },
    "completedAt": "2026-02-14T01:36:02.863Z"
  },
  "phase2": {
    "status": "running",
    "queries": [
      "Q1",
      "Q3",
      "Q6"
    ],
    "maxConcurrent": 5,
    "pipelines": {}
  }
}