{
  "compile": {
    "status": "pass",
    "output": {
      "stdout": "",
      "stderr": "In file included from /home/jl4492/GenDB/output/tpc-h/2026-02-21T23-00-40/queries/Q18/iter_0/q18.cpp:19:\n/home/jl4492/GenDB/src/gendb/utils/date_utils.h: In function ‘void run_Q18(const string&, const string&)’:\n/home/jl4492/GenDB/src/gendb/utils/date_utils.h:52:38: warning: ‘__builtin___sprintf_chk’ may write a terminating nul past the end of the destination [-Wformat-overflow=]\n   52 |     std::sprintf(buf, \"%04d-%02d-%02d\", y, m, d);\n      |                                      ^\nIn file included from /usr/include/stdio.h:894,\n                 from /usr/include/c++/11/cstdio:42,\n                 from /home/jl4492/GenDB/output/tpc-h/2026-02-21T23-00-40/queries/Q18/iter_0/q18.cpp:5:\n/usr/include/x86_64-linux-gnu/bits/stdio2.h:38:34: note: ‘__builtin___sprintf_chk’ output between 11 and 17 bytes into a destination of size 16\n   38 |   return __builtin___sprintf_chk (__s, __USE_FORTIFY_LEVEL - 1,\n      |          ~~~~~~~~~~~~~~~~~~~~~~~~^~~~~~~~~~~~~~~~~~~~~~~~~~~~~~\n   39 |                                   __glibc_objsize (__s), __fmt,\n      |                                   ~~~~~~~~~~~~~~~~~~~~~~~~~~~~~\n   40 |                                   __va_arg_pack ());\n      |                                   ~~~~~~~~~~~~~~~~~\n"
    }
  },
  "run": {
    "status": "pass",
    "output": "[TIMING] data_loading: 68.73 ms\n[TIMING] dim_filter: 467.34 ms\n[TIMING] build_joins: 1735.99 ms\n[TIMING] main_scan: 6.40 ms\n[TIMING] output: 0.99 ms\n[TIMING] total: 2279.86 ms\n",
    "stderr": "",
    "duration_ms": 2309
  },
  "validation": {
    "status": "pass",
    "output": "{\n  \"match\": true,\n  \"queries\": {\n    \"Q18\": {\n      \"rows_expected\": 100,\n      \"rows_actual\": 100,\n      \"match\": true\n    }\n  }\n}\n"
  },
  "operation_timings": {
    "data_loading": 76,
    "dim_filter": 461.61,
    "build_joins": 1765.94,
    "main_scan": 4.74,
    "output": 0.46,
    "total": 2309.12
  },
  "timing_ms": 4608.085,
  "cold_timing_ms": 2308.66,
  "hot_timing_ms": 2299.425,
  "hot_operation_timings": {
    "data_loading": 68.73,
    "dim_filter": 467.34,
    "build_joins": 1735.99,
    "main_scan": 6.4,
    "output": 0.99,
    "total": 2279.86
  },
  "all_runs": [
    {
      "timing_ms": 2308.66,
      "operation_timings": {
        "data_loading": 76,
        "dim_filter": 461.61,
        "build_joins": 1765.94,
        "main_scan": 4.74,
        "output": 0.46,
        "total": 2309.12
      }
    },
    {
      "timing_ms": 2319.98,
      "operation_timings": {
        "data_loading": 69.58,
        "dim_filter": 455.68,
        "build_joins": 1785.27,
        "main_scan": 9.03,
        "output": 0.47,
        "total": 2320.45
      }
    },
    {
      "timing_ms": 2278.8700000000003,
      "operation_timings": {
        "data_loading": 68.73,
        "dim_filter": 467.34,
        "build_joins": 1735.99,
        "main_scan": 6.4,
        "output": 0.99,
        "total": 2279.86
      }
    }
  ]
}